file_grouper/__init__.py
file_grouper/console.py
file_grouper/file_grouper.py
file_grouper-0.1.2.dist-info/entry_points.txt
file_grouper-0.1.2.dist-info/LICENSE
file_grouper-0.1.2.dist-info/WHEEL
file_grouper-0.1.2.dist-info/METADATA
file_grouper-0.1.2.dist-info/RECORD
